coqui/__init__.py
coqui/__main__.py
coqui-0.0.10.dist-info/entry_points.txt
coqui-0.0.10.dist-info/LICENSE
coqui-0.0.10.dist-info/WHEEL
coqui-0.0.10.dist-info/METADATA
coqui-0.0.10.dist-info/RECORD
