Metadata-Version: 2.1
Name: coqui
Version: 0.0.10
Summary: A Python API and CLI to use Coqui services programmatically 
Author-email: "coqui.ai" <info@coqui.ai>
Requires-Python: >=3.7,<3.12
Classifier: Development Status :: 4 - Beta
Classifier: Intended Audience :: Developers
Classifier: Topic :: Multimedia :: Sound/Audio :: Speech
Classifier: Programming Language :: Python :: 3
Classifier: License :: OSI Approved :: Apache Software License
Requires-Dist: click==8.1.3
Requires-Dist: gql[aiohttp]==3.3.0
Requires-Dist: json5==0.9.8
Requires-Dist: Sphinx==6.1.3 ; extra == "docs"
Requires-Dist: sphinx-immaterial==0.11.2 ; extra == "docs"
Project-URL: Home, https://github.com/coqui-ai/coqui-py
Project-URL: Source, https://github.com/coqui-ai/coqui-py
Provides-Extra: docs
